{
  "global": {
    "en": {
      "name": "Bra7tak",
      "searchHint": "Search by name, code, etc...",
      "flashSell": "Flash Sell",
      "offerEndsIn": "Offer ends in:",
      "bio": "Lorem ipsum dolor sit amet, consectetur adipiscing elit. Phasellus vitae mauris in tortor ornare mollis ac nec nisi. Donec in felis dui. Sed velit tellus, convallis nec congue et, vulputate sit amet sem. Aliquam lorem tellus, faucibus at eros in, facilisis tristique ipsum. Vestibulum a pretium quam. Suspendisse tristique purus ac arcu maximus, vel malesuada sapien dictum. Sed a convallis lectus.",
      "filter": "Filter",
      "filterMsg": "Lorem ipsum dolor sit amet, consectetur adipiscing elit.",
      "category": "Category",
      "categoryMsg": "Lorem ipsum dolor sit amet, consectetur adipiscing elit.",
      "subcategory": "Sub Category",
      "subcategoryMsg": "Lorem ipsum dolor sit amet, consectetur adipiscing elit.",
      "price": "Price",
      "priceMsg": "Lorem ipsum dolor sit amet, consectetur adipiscing elit.",
      "searchMsg": "Lorem ipsum dolor sit amet, consectetur adipiscing elit.",
      "minPrice": "Minimum Price",
      "maxPrice": "Maximum Price",
      "code": "Code",
      "discount": "Discount",
      "productInformation": "Product Information",
      "delivery": "Delivery",
      "discountPercentOff": "off Discount Percent",
      "userId": "User Id",
      "userName": "Name",
      "joinedIn": "Joined In",
      "address": "Address",
      "city": "City",
      "gender": "Gender",
      "userHasNoOrders": "You have placed no orders, Start Ordering Now!",
      "orders": "Orders",
      "canceled": "Cancelled",
      "stocked": "Stocked",
      "delivering": "Delivering",
      "delivered": "Delivered",
      "userHasNoProductsInCart": "You have no products in your cart, Add Some Now!",
      "userHasNoProductsInFavourites": "It seems like no product catched your attension yet, See Recommendations!",
      "completeProfile": "Complete Profile",
      "phoneNumber": "Phone Number",
      "products": "Products",
      "reciept": "Reciept",
      "productsPrice": "Products Price",
      "vat": "Vat",
      "shippingFees": "Shipping Fees",
      "totalPrice": "Total Price",
      "basedOnYourChoises": "Based On Your Choises",
      "welcomeBack": "Welcome Back",
      "notFoundProduct": "The product you're searching for maybe deleted or unavailable right now!",
      "notFoundCollection": "The collection you're searching for maybe deleted or unavailable right now!",
      "notFoundCategory": "The category you're searching for maybe deleted or unavailable right now!",
      "personalInformation": "Personal Information",
      "ShippingInformation": "Shipping Information",
      "PaymentInformation": "Payment Information",
      "CompleteOrder": "Complete Order",
      "addressOne": "Address Line 1",
      "addressTwo": "Address Line 2",
      "addressThree": "Building Number, Flat / Appartment",
      "shippingDays": "Shipping Days",
      "cashOnDelivery": "Cach on Delivery",
      "paypal": "Paypal",
      "creditCard": "Credit Card",
      "points": "Points",
      "vouchers": "Vouchers",
      "comingSoon": "Coming Soon!",
      "orderCompletedSuccessfullyMsg": "Your order is under review right now! An Agent from Bra7tak will contact you soon!",
      "avg_del_days": "Average Delivery Days",
      "optional": "Optional",
      "fullName": "Full Name"
    },
    "ar": {
      "name": "براحتك",
      "searchHint": "البحث بالاسم، الكود، وغيره...",
      "flashSell": "فلاش سيل",
      "offerEndsIn": "ينتهي العرض في:",
      "bio": "Lorem ipsum dolor sit amet, consectetur adipiscing elit. Phasellus vitae mauris in tortor ornare mollis ac nec nisi. Donec in felis dui. Sed velit tellus, convallis nec congue et, vulputate sit amet sem. Aliquam lorem tellus, faucibus at eros in, facilisis tristique ipsum. Vestibulum a pretium quam. Suspendisse tristique purus ac arcu maximus, vel malesuada sapien dictum. Sed a convallis lectus.",
      "filter": "فلتر",
      "filterMsg": "Lorem ipsum dolor sit amet, consectetur adipiscing elit.",
      "category": "الفئة",
      "categoryMsg": "Lorem ipsum dolor sit amet, consectetur adipiscing elit.",
      "subcategory": "الفئة الفرعية",
      "subcategoryMsg": "Lorem ipsum dolor sit amet, consectetur adipiscing elit.",
      "price": "السعر",
      "priceMsg": "Lorem ipsum dolor sit amet, consectetur adipiscing elit.",
      "searchMsg": "Lorem ipsum dolor sit amet, consectetur adipiscing elit.",
      "minPrice": "أقل سعر",
      "maxPrice": "أعلى سعر",
      "code": "الكود",
      "discount": "تخفيض",
      "productInformation": "معلومات المنتج",
      "delivery": "التوصيل",
      "discountPercentOff": "نسبة الخصم",
      "userId": "هوية المستخدم",
      "userName": "الاسم",
      "joinedIn": "انضم في",
      "address": "العنوان",
      "city": "المدينة",
      "gender": "النوع",
      "userHasNoOrders": "لم تسجل أي طلبات، اطلب الآن!",
      "orders": "الطلبات",
      "canceled": "الطلبات التي تم إلغاؤها",
      "stocked": "المخزون",
      "delivering": "جاري التسليم",
      "delivered": "تم التسليم",
      "userHasNoProductsInCart": "لا توجد منتجات في سلة مشترياتك، ضع البعض الآن!",
      "userHasNoProductsInFavourites": "يبدو أن لم يلفت انتباهك منتجات، انظر ترشيحات!",
      "completeProfile": "اكمل الملف الشخصي",
      "phoneNumber": "رقم الهاتف المحمول",
      "products": "المنتجات",
      "reciept": "الفاتورة",
      "productsPrice": "سعر المنتجات",
      "vat": "الضريبة",
      "shippingFees": "رسوم التوصيل",
      "totalPrice": "المبلغ الكُلي",
      "basedOnYourChoises": "وفقاً لاختياراتك",
      "welcomeBack": "مرحباً بعودتك",
      "notFoundProduct": "يبدو أن المنتج الذي تبحث عنه قد تم حذفه أو غير متوفر الآن!",
      "notFoundCollection": "يبدو أن المجموعة الذي تبحث عنها قد تم حذفها أو غير متوفرة الآن!",
      "notFoundCategory": "يبدو أن الفئة الذي تبحث عنها قد تم حذفها أو غير متوفرة الآن!",
      "personalInformation": "المعلومات الشخصية",
      "ShippingInformation": "معلومات التوصيل",
      "PaymentInformation": "معلومات الدفع",
      "CompleteOrder": "اكمل الطلب",
      "addressOne": "سطرالعنوان 1",
      "addressTwo": "سطر العنوان 2",
      "addressThree": "رقم المبنى، الشقة",
      "shippingDays": "أيام التوصيل",
      "cashOnDelivery": "الدفع عند الاستلام",
      "paypal": "Paypal",
      "creditCard": "Credit Card",
      "points": "النقاط",
      "vouchers": "قسائم الشراء",
      "comingSoon": "قريباً",
      "orderCompletedSuccessfullyMsg": "طلبك تحت المراجعة!سيتواصل معك وكيل من براحتك قريباً!",
      "avg_del_days": "متوسط أيام التوصيل",
      "optional": "اختياري",
      "fullName": "الاسم بالكامل"
    }
  },

  "actions": {
    "en": {
      "apply": "Apply",
      "clear": "Clear",
      "close": "Close",
      "search": "Search",
      "seeMore": "See More",
      "addToCart": "Add to Cart",
      "orderNow": "Order now",
      "editProfile": "Edit Profile",
      "getStarted": "Get Started",
      "downlowdInvoice": "Downlowd Invoice",
      "submit": "Submit",
      "pickCity": "Pick City",
      "pickGender": "Pick Gender",
      "removeUnit": "Remove Unit",
      "removeAll": "Remove All",
      "checkout": "Checkout",
      "emptyCart": "Empty Cart",
      "seeAll": "see All",
      "logout": "Logout",
      "completeShopping": "Complete Shopping",
      "buy": "Buy",
      "save": "Save"
    },
    "ar": {
      "apply": "تطبيق",
      "clear": "مسح",
      "close": "إغلاق",
      "search": "بحث",
      "seeMore": "مشاهدة المزيد",
      "addToCart": "إضافة إلى سلة المشتريات",
      "orderNow": "الطلب الآن",
      "editProfile": "تعديل الملف الشخصي",
      "getStarted": "ابدء",
      "downlowdInvoice": "تنزيل الفاتورة",
      "submit": "تسليم",
      "pickCity": "اختر مدينة",
      "pickGender": "اختر النوع",
      "removeUnit": "حذف الوحدة",
      "removeAll": "حذف الكل",
      "checkout": "الدفع",
      "emptyCart": "سلة المشتريات فارغة",
      "seeAll": "رؤية الكل",
      "logout": "تسجيل الخروج",
      "completeShopping": "اكمال التسوق",
      "buy": "شراء",
      "save": "حفظ"
    }
  },

  "tabs": {
    "en": {
      "home": "Home",
      "login": "Login",
      "signup": "SignUp",
      "account": "Account",
      "products": "Products",
      "cart": "Cart",
      "favourites": "Favourites",
      "categories": "Categories",
      "socialMedia": "Social Media"
    },
    "ar": {
      "home": "الصفحة الرئيسية",
      "login": "تسجيل الدخول",
      "signup": "التسجيل",
      "account": "الحساب",
      "products": "المنتجات",
      "cart": "سلة المشتريات",
      "favourites": "المفضلة",
      "categories": "الفئات",
      "socialMedia": "وسائل التواصل الاجتماعي"
    }
  },

  "auth": {
    "en": {
      "email": "Email",
      "phone": "Phone",
      "username": "Username",
      "password": "Password",
      "repassword": "Re-Password",
      "login": "Login",
      "logout": "Logout",
      "signup": "Sign Up",
      "forgetPassword": "Forget Password?",
      "rememberMe": "Remember me",
      "newUserMessage": "Don't have account? Sign up now!",
      "existingUserMessage": "Already have account? Login now!",
      "content": "Lorem ipsum dolor sit amet, consectetur adipiscing elit. Suspendisse lacus nibh, sagittis a ante eu, luctus fringilla est. Aliquam pulvinar justo iaculis lorem pretium elementum. In mauris quam, porttitor nec venenatis in, vulputate non arcu. Aliquam ac iaculis nisl. Morbi sit amet ante justo. Donec lectus erat, molestie at gravida in, convallis a massa. Aenean rutrum vel ligula consequat convallis. Suspendisse nec leo leo. Donec non mi nec eros consequat facilisis. In condimentum et libero ut hendrerit. Nullam scelerisque mauris ac nunc ultricies, eget tincidunt sapien ullamcorper.",
      "confirmEmail": "Confrim you email!",
      "confirmEmailMsg": "Enter the code that was delivered with an email has been sent to your email",
      "sendCodeAgain": "Send verification code again",
      "changeEmail": "Change Email"
    },
    "ar": {
      "email": "البريد الالكتروني",
      "phone": "الهاتف المحمول",
      "username": "اسم المستخدم",
      "password": "كلمة المرور",
      "repassword": "إعادة كلمة المرور",
      "login": "تسجيل الدخول",
      "logout": "تسجيل الخروج",
      "signup": "التسجيل",
      "forgetPassword": "نسيت كلمة المرور؟",
      "rememberMe": "تذكرني",
      "newUserMessage": "ليس لديك حساب؟ التسجيل الآن!",
      "existingUserMessage": "بالفعل لديك حساب؟ تسجيل الدخول!",
      "content": "Lorem ipsum dolor sit amet, consectetur adipiscing elit. Suspendisse lacus nibh, sagittis a ante eu, luctus fringilla est. Aliquam pulvinar justo iaculis lorem pretium elementum. In mauris quam, porttitor nec venenatis in, vulputate non arcu. Aliquam ac iaculis nisl. Morbi sit amet ante justo. Donec lectus erat, molestie at gravida in, convallis a massa. Aenean rutrum vel ligula consequat convallis. Suspendisse nec leo leo. Donec non mi nec eros consequat facilisis. In condimentum et libero ut hendrerit. Nullam scelerisque mauris ac nunc ultricies, eget tincidunt sapien ullamcorper.",
      "confirmEmail": "تأكيد البريد الالكتروني",
      "confirmEmailMsg": "أدخل الرمز الذي تم إرساله إلى بريدك الاكتروني",
      "sendCodeAgain": "إعادة إرسال رمز التحقق",
      "changeEmail": "تغيير الايميل"
    }
  }
}
